ablean/__init__.py
ablean/constants.py
ablean/container.py
ablean/data_manager.py
ablean/main.py
ablean/myclick.py
ablean/commands/__init__.py
ablean/commands/backtest.py
ablean/commands/create_project.py
ablean/commands/download.py
ablean/commands/init.py
ablean/components/__init__.py
ablean/components/lean_runner.py
ablean/components/module_manager.py
ablean/components/config/__init__.py
ablean/components/config/cli_config_manager.py
ablean/components/config/lean_config_manager.py
ablean/components/config/output_config_manager.py
ablean/components/config/project_config_manager.py
ablean/components/config/storage.py
ablean/components/util/__init__.py
ablean/components/util/logger.py
ablean/components/util/name_extraction.py
ablean/components/util/name_generator.py
ablean/components/util/path_manager.py
ablean/components/util/platform_manager.py
ablean/components/util/project_manager.py
ablean/components/util/temp_manager.py
ablean/components/util/xml_manager.py
ablean/icons/icon.icns
ablean/icons/icon.ico
ablean/models/__init__.py
ablean/models/errors.py
ablean/models/modules.py
ablean/models/options.py
ablean/models/pydantic.py
ablean/models/utils.py
ablean-1.3.13.dist-info/METADATA
ablean-1.3.13.dist-info/WHEEL
ablean-1.3.13.dist-info/entry_points.txt
ablean-1.3.13.dist-info/top_level.txt
ablean-1.3.13.dist-info/RECORD
