Metadata-Version: 2.1
Name: ablean
Version: 1.3.13
Summary: A CLI aimed at making it easier to run QuantConnect's LEAN engine locally and in the cloud
Home-page: https://lean.io/cli
Author: abl
Author-email: support@quantconnect.com
Project-URL: Documentation, https://www.lean.io/docs/lean-cli/key-concepts/getting-started
Project-URL: Source, https://github.com/QuantConnect/lean-cli
Classifier: Development Status :: 5 - Production/Stable
Classifier: Intended Audience :: Developers
Classifier: Intended Audience :: Financial and Insurance Industry
Classifier: License :: OSI Approved :: Apache Software License
Classifier: Programming Language :: Python :: 3
Classifier: Programming Language :: Python :: 3.6
Classifier: Programming Language :: Python :: 3.7
Classifier: Programming Language :: Python :: 3.8
Classifier: Programming Language :: Python :: 3.9
Requires-Python: >= 3.8
Requires-Dist: click (~=8.1.3)
Requires-Dist: requests (~=2.25.1)
Requires-Dist: json5 (~=0.9.5)
Requires-Dist: rich (~=12.4.4)
Requires-Dist: dependency-injector (~=4.20.1)
Requires-Dist: pydantic (~=1.7.3)
Requires-Dist: python-dateutil (~=2.8.1)
Requires-Dist: lxml (~=4.6.3)
Requires-Dist: maskpass (==0.3.5)
Requires-Dist: joblib (~=1.0.1)
Requires-Dist: python-certifi-win32 (~=1.6)
Requires-Dist: pyshortcuts (~=1.8.0)
Requires-Dist: wrapt (~=1.12.1)
Requires-Dist: paramiko (~=2.11.0)
Requires-Dist: scp (~=0.14.4)
Requires-Dist: ptvsd
Requires-Dist: setuptools
Requires-Dist: abl-quantconnect-stubs (>=13987.7)
